setup.py
doodle_dashboard_console_display.egg-info/PKG-INFO
doodle_dashboard_console_display.egg-info/SOURCES.txt
doodle_dashboard_console_display.egg-info/dependency_links.txt
doodle_dashboard_console_display.egg-info/entry_points.txt
doodle_dashboard_console_display.egg-info/requires.txt
doodle_dashboard_console_display.egg-info/top_level.txt
sketchingdev/__about__.py
sketchingdev/__init__.py
sketchingdev/custom.py