Metadata-Version: 1.2
Name: doodle-dashboard-console-display
Version: 0.0.7
Summary: Console display for Doodle-Dashboard.
Home-page: https://github.com/SketchingDev/Doodle-Dashboard-Console-Display
License: MIT
Platform: UNKNOWN
Classifier: Development Status :: 3 - Alpha
Classifier: Programming Language :: Python :: 3.4
Requires-Python: >=3.4
